{
    "file_name": "manuscript.md",
    "title": "Time as Reading Depth",
    "registry_id": "HOWL-PHYS-41-2026",
    "series_path": "[@HOWL-PHYS-1-2026] \u2192 [@HOWL-PHYS-24-2026] \u2192 [@HOWL-PHYS-40-2026] \u2192 [@HOWL-PHYS-41-2026]",
    "doi": "10.5281/zenodo.19673837",
    "abstract": "",
    "dependencies": [],
    "raw_content_preview": "# Time as Reading Depth ## The Fourth Coordinate Reinterpreted  ### Registry: [@HOWL-PHYS-41-2026]  **Series Path:** [@HOWL-PHYS-1-2026] \u2192 [@HOWL-PHYS-24-2026] \u2192 [@HOWL-PHYS-40-2026] \u2192 [@HOWL-PHYS-41-..."
}