{
  "nodes": [
    {
      "key": "program_beta_unification_v0",
      "canonical": "program_beta_unification",
      "version": 0,
      "node_type": "program",
      "topic": "program",
      "term": "beta_unification",
      "level": null,
      "source": "Session 4",
      "thesis": "Gauge group beta coefficient integers determine cosmological parameters",
      "status": "ACTIVE",
      "tags": [
        "beta",
        "unification",
        "cosmology"
      ],
      "scripts": [
        {
          "name": "beta_unification_test.py",
          "description": "15 cosmological predictions from particle physics integers",
          "stage": 1
        }
      ],
      "kill_switches": [
        {
          "name": "coincidence_probability",
          "condition": "p > 0.1 for observed integer matches",
          "data_source": "combinatoric analysis"
        },
        {
          "name": "cmb_s4_omega",
          "condition": "Omega_DM moves away from 44/169 with CMB-S4 data",
          "data_source": "CMB-S4 / LiteBIRD"
        }
      ],
      "program_connections": {
        "program_toroidal_dm": "shares integers 22, 13, 44",
        "program_hubble_running": "shares integer 20/13"
      }
    },
    {
      "key": "program_toroidal_dm_v0",
      "canonical": "program_toroidal_dm",
      "version": 0,
      "node_type": "program",
      "topic": "program",
      "term": "toroidal_dm",
      "level": null,
      "source": "Session 4",
      "thesis": "DM amplification via toroidal circulation A=(44/13)*pi*(c/v)^2",
      "status": "ACTIVE",
      "tags": [
        "DM",
        "toroidal",
        "amplification"
      ],
      "scripts": [
        {
          "name": "toroidal_tidal_stripping.py",
          "description": "Quantify tidal stripping in dwarfs",
          "stage": 1
        }
      ],
      "kill_switches": [
        {
          "name": "wimp_detection",
          "condition": "Direct detection of DM particles",
          "data_source": "LZ / XENONnT / PandaX"
        },
        {
          "name": "dwarf_virial",
          "condition": "Virial theorem cannot be rescued for dwarfs",
          "data_source": "dwarf_soliton_ground_state.py"
        }
      ],
      "program_connections": {
        "program_beta_unification": "A numerator 44/13 from betas"
      }
    },
    {
      "key": "program_hubble_running_v0",
      "canonical": "program_hubble_running",
      "version": 0,
      "node_type": "program",
      "topic": "program",
      "term": "hubble_running",
      "level": null,
      "source": "Session 4",
      "thesis": "H0 decreases with boundary transit count: H0(N) = H0(0)*r^N",
      "status": "ACTIVE",
      "tags": [
        "Hubble",
        "running",
        "cosmology"
      ],
      "scripts": [
        {
          "name": "hubble_structure_catalog.py",
          "description": "Extract N estimates from galaxy surveys",
          "stage": 1
        }
      ],
      "kill_switches": [
        {
          "name": "gw_sirens",
          "condition": "GW standard sirens show same running as EM",
          "data_source": "LIGO/Virgo O5+"
        },
        {
          "name": "systematic_resolution",
          "condition": "Systematic error found resolving H0 tension without running",
          "data_source": "SH0ES / Planck reanalysis"
        }
      ],
      "program_connections": {
        "program_beta_unification": "(1-r) = alpha^2*pi^2*(20/13)"
      }
    }
  ]
}